{
  "project_info": {
    "project_number": "618106742901",
    "project_id": "ictd-d42c2",
    "storage_bucket": "ictd-d42c2.firebasestorage.app"
  },
  "client": [
    {
      "client_info": {
        "mobilesdk_app_id": "1:618106742901:android:ac046b191d8f012eb6b03c",
        "android_client_info": {
          "package_name": "com.company.ictd"
        }
      },
      "oauth_client": [],
      "api_key": [
        {
          "current_key": "AIzaSyAb3JZe7dd4KDxRUo-dlecfFzp0Wy6oj04"
        }
      ],
      "services": {
        "appinvite_service": {
          "other_platform_oauth_client": []
        }
      }
    },
    {
      "client_info": {
        "mobilesdk_app_id": "1:618106742901:android:1a59daac3f26d8d7b6b03c",
        "android_client_info": {
          "package_name": "com.yangoprojet"
        }
      },
      "oauth_client": [],
      "api_key": [
        {
          "current_key": "AIzaSyAb3JZe7dd4KDxRUo-dlecfFzp0Wy6oj04"
        }
      ],
      "services": {
        "appinvite_service": {
          "other_platform_oauth_client": []
        }
      }
    }
  ],
  "configuration_version": "1"
}